<annotation>
	<folder>violet</folder>
	<filename>violet7.jpg</filename>
	<path>/home/hanlinchen/Desktop/weeds_detections/images/violet/violet7.jpg</path>
	<source>
		<database>Unknown</database>
	</source>
	<size>
		<width>995</width>
		<height>945</height>
		<depth>3</depth>
	</size>
	<segmented>0</segmented>
	<object>
		<name>violet</name>
		<pose>Unspecified</pose>
		<truncated>0</truncated>
		<difficult>0</difficult>
		<bndbox>
			<xmin>115</xmin>
			<ymin>113</ymin>
			<xmax>891</xmax>
			<ymax>810</ymax>
		</bndbox>
	</object>
</annotation>
