<annotation>
	<folder>violet</folder>
	<filename>violet175.jpg</filename>
	<path>/home/hanlinchen/Desktop/weeds_detections/images/violet/violet175.jpg</path>
	<source>
		<database>Unknown</database>
	</source>
	<size>
		<width>640</width>
		<height>427</height>
		<depth>3</depth>
	</size>
	<segmented>0</segmented>
	<object>
		<name>violet</name>
		<pose>Unspecified</pose>
		<truncated>0</truncated>
		<difficult>0</difficult>
		<bndbox>
			<xmin>328</xmin>
			<ymin>95</ymin>
			<xmax>501</xmax>
			<ymax>310</ymax>
		</bndbox>
	</object>
	<object>
		<name>violet</name>
		<pose>Unspecified</pose>
		<truncated>0</truncated>
		<difficult>0</difficult>
		<bndbox>
			<xmin>27</xmin>
			<ymin>309</ymin>
			<xmax>144</xmax>
			<ymax>419</ymax>
		</bndbox>
	</object>
</annotation>
