<annotation>
	<folder>crabgrass</folder>
	<filename>crabgrass239.jpg</filename>
	<path>/home/hanlinchen/Desktop/weeds_detections/images/crabgrass/crabgrass239.jpg</path>
	<source>
		<database>Unknown</database>
	</source>
	<size>
		<width>480</width>
		<height>360</height>
		<depth>3</depth>
	</size>
	<segmented>0</segmented>
	<object>
		<name>crabgrass</name>
		<pose>Unspecified</pose>
		<truncated>0</truncated>
		<difficult>0</difficult>
		<bndbox>
			<xmin>108</xmin>
			<ymin>70</ymin>
			<xmax>432</xmax>
			<ymax>285</ymax>
		</bndbox>
	</object>
</annotation>
