<annotation>
	<folder>dandelion</folder>
	<filename>dandelion143.jpg</filename>
	<path>/home/hanlinchen/Desktop/weeds_detections/images/dandelion/dandelion143.jpg</path>
	<source>
		<database>Unknown</database>
	</source>
	<size>
		<width>334</width>
		<height>500</height>
		<depth>3</depth>
	</size>
	<segmented>0</segmented>
	<object>
		<name>dandelion</name>
		<pose>Unspecified</pose>
		<truncated>0</truncated>
		<difficult>0</difficult>
		<bndbox>
			<xmin>199</xmin>
			<ymin>233</ymin>
			<xmax>274</xmax>
			<ymax>284</ymax>
		</bndbox>
	</object>
	<object>
		<name>dandelion</name>
		<pose>Unspecified</pose>
		<truncated>0</truncated>
		<difficult>0</difficult>
		<bndbox>
			<xmin>7</xmin>
			<ymin>367</ymin>
			<xmax>65</xmax>
			<ymax>407</ymax>
		</bndbox>
	</object>
	<object>
		<name>dandelion</name>
		<pose>Unspecified</pose>
		<truncated>0</truncated>
		<difficult>0</difficult>
		<bndbox>
			<xmin>6</xmin>
			<ymin>285</ymin>
			<xmax>55</xmax>
			<ymax>322</ymax>
		</bndbox>
	</object>
	<object>
		<name>dandelion</name>
		<pose>Unspecified</pose>
		<truncated>0</truncated>
		<difficult>0</difficult>
		<bndbox>
			<xmin>294</xmin>
			<ymin>343</ymin>
			<xmax>331</xmax>
			<ymax>378</ymax>
		</bndbox>
	</object>
</annotation>
